.coveragerc
CHANGES.rst
MANIFEST.in
README.rst
setup.cfg
setup.py
build_commands/__init__.py
build_commands/bower.py
build_commands/gulp.py
build_commands/npm.py
build_commands.egg-info/PKG-INFO
build_commands.egg-info/SOURCES.txt
build_commands.egg-info/dependency_links.txt
build_commands.egg-info/entry_points.txt
build_commands.egg-info/not-zip-safe
build_commands.egg-info/pbr.json
build_commands.egg-info/requires.txt
build_commands.egg-info/top_level.txt
build_commands/tests/test_bower.py
build_commands/tests/test_gulp.py
build_commands/tests/test_npm.py