Metadata-Version: 1.1
Name: build-commands
Version: 0.0.1
Summary: build_commands
Home-page: https://github.com/davidemoro/build_commands
Author: Davide Moro
Author-email: davide.moro@gmail.com
License: UNKNOWN
Keywords: web python gulp npm bower yeoman
Platform: UNKNOWN
Classifier: Programming Language :: Python
Classifier: Topic :: Internet :: WWW/HTTP
